dm_utils/__init__.py
dm_utils/data_load.py
dm_utils/display.py
tests/__init__.py
tests/test_data_load.py
tests/test_display.py
dm_touka_utils-0.0.0.dist-info/METADATA
dm_touka_utils-0.0.0.dist-info/WHEEL
dm_touka_utils-0.0.0.dist-info/top_level.txt
dm_touka_utils-0.0.0.dist-info/RECORD
